hubspace_da/__init__.py
hubspace_da/api_interface.py
hubspace_da/api_interface_github.py
hubspace_da/hsdev_manager.py
hubspace_da-1.0.10.dist-info/METADATA
hubspace_da-1.0.10.dist-info/WHEEL
hubspace_da-1.0.10.dist-info/RECORD
