Metadata-Version: 2.1
Name: hubspace-da
Version: 1.0.10
Summary: 
Author: Al DAmico
Author-email: JavaWiz1@hotmail.com
Requires-Python: >=3.10,<4.0
Classifier: Programming Language :: Python :: 3
Classifier: Programming Language :: Python :: 3.10
Classifier: Programming Language :: Python :: 3.11
Classifier: Programming Language :: Python :: 3.12
Requires-Dist: dt-console (>=0.1.8,<0.2.0)
Requires-Dist: dt-net (>=0.1.6,<0.2.0)
Requires-Dist: requests (>=2.31,<3.0)
